hail/__init__.py
hail/conftest.py
hail/context.py
hail/hail_logging.py
hail/hail_pip_version
hail/hail_version
hail/matrixtable.py
hail/table.py
hail/backend/__init__.py
hail/backend/backend.py
hail/backend/hail-all-spark.jar
hail/backend/local_backend.py
hail/backend/py4j_backend.py
hail/backend/service_backend.py
hail/backend/spark_backend.py
hail/docs/__init__.py
hail/docs/conf.py
hail/experimental/__init__.py
hail/experimental/codec.py
hail/experimental/compile.py
hail/experimental/datasets.json
hail/experimental/datasets.py
hail/experimental/db.py
hail/experimental/export_entries_by_col.py
hail/experimental/expressions.py
hail/experimental/filtering_allele_frequency.py
hail/experimental/full_outer_join_mt.py
hail/experimental/function.py
hail/experimental/haplotype_freq_em.py
hail/experimental/import_gtf.py
hail/experimental/interact.py
hail/experimental/ld_score_regression.py
hail/experimental/ldscore.py
hail/experimental/ldscsim.py
hail/experimental/lens.py
hail/experimental/loop.py
hail/experimental/pca.py
hail/experimental/phase_by_transmission.py
hail/experimental/plots.py
hail/experimental/tidyr.py
hail/experimental/time.py
hail/experimental/write_multiple.py
hail/experimental/dnd/__init__.py
hail/experimental/dnd/array.py
hail/experimental/vcf_combiner/__init__.py
hail/experimental/vcf_combiner/__main__.py
hail/experimental/vcf_combiner/densify.py
hail/experimental/vcf_combiner/sparse_mt_utils.py
hail/experimental/vcf_combiner/sparse_split_multi.py
hail/experimental/vcf_combiner/vcf_combiner.py
hail/expr/__init__.py
hail/expr/blockmatrix_type.py
hail/expr/builders.py
hail/expr/functions.py
hail/expr/matrix_type.py
hail/expr/nat.py
hail/expr/table_type.py
hail/expr/type_parsing.py
hail/expr/types.py
hail/expr/aggregators/__init__.py
hail/expr/aggregators/aggregators.py
hail/expr/expressions/__init__.py
hail/expr/expressions/base_expression.py
hail/expr/expressions/expression_typecheck.py
hail/expr/expressions/expression_utils.py
j11hail-99.2.58.dist-info/METADATA
j11hail-99.2.58.dist-info/WHEEL
j11hail-99.2.58.dist-info/entry_points.txt
j11hail-99.2.58.dist-info/top_level.txt
j11hail-99.2.58.dist-info/RECORD
