Metadata-Version: 2.1
Name: j11hail
Version: 99.2.58
Summary: Scalable library for exploring and analyzing genomic data.
Home-page: https://hail.is
Author: Hail Team
Author-email: hail@broadinstitute.org
License: UNKNOWN
Project-URL: Documentation, https://hail.is/docs/0.2/
Project-URL: Repository, https://github.com/hail-is/hail
Platform: UNKNOWN
Classifier: Programming Language :: Python :: 3
Classifier: License :: OSI Approved :: MIT License
Requires-Python: >=3.6
Requires-Dist: aiohttp (<3.7,>=3.6)
Requires-Dist: aiohttp-session (<2.8,>=2.7)
Requires-Dist: asyncinit (<0.3,>=0.2.4)
Requires-Dist: bokeh (<1.3,>1.1)
Requires-Dist: decorator (<5)
Requires-Dist: Deprecated (<1.3,>=1.2.10)
Requires-Dist: dill (<0.4,>=0.3.1.1)
Requires-Dist: gcsfs (==0.2.2)
Requires-Dist: humanize (==1.0.0)
Requires-Dist: hurry.filesize (==0.9)
Requires-Dist: nest-asyncio
Requires-Dist: numpy (<2)
Requires-Dist: pandas (<0.26,>0.24)
Requires-Dist: parsimonious (<0.9)
Requires-Dist: PyJWT
Requires-Dist: pyspark (==3.0.0)
Requires-Dist: python-json-logger (==0.1.11)
Requires-Dist: requests (==2.22.0)
Requires-Dist: scipy (<1.4,>1.2)
Requires-Dist: tabulate (==0.8.3)
Requires-Dist: tqdm (==4.42.1)
Requires-Dist: google-cloud-storage (==1.25.*)
